Metadata-Version: 2.1
Name: nnprof
Version: 0.1.1
Summary: Profile tool for neural network(time, memory, etc.)
Home-page: https://github.com/FateScript/nnprof
Author: Feng Wang
Author-email: wffatescript@gmail.com
License: Apache License 2.0
Platform: UNKNOWN
Classifier: License :: OSI Approved :: Apache Software License
Classifier: Operating System :: OS Independent
Classifier: Programming Language :: Python :: 2
Classifier: Programming Language :: Python :: 3
Classifier: Programming Language :: Python :: 3.5
Classifier: Programming Language :: Python :: 3.6
Classifier: Programming Language :: Python :: 3.7
Classifier: Programming Language :: Python :: 3.8
Classifier: Programming Language :: Python :: 3.9
